funhandler/__init__.py
funhandler/base.py
funhandler/config.py
funhandler/data.py
funhandler/execution.py
funhandler/file_manager.py
funhandler/handler.py
funhandler/helpers.py
funhandler/session.py
funhandler/state.py
funhandler/stoch_gen.py
funhandler/blocks/__init__.py
funhandler/blocks/base.py
funhandler/blocks/world.py
funhandler/blocks/actions/__init__.py
funhandler/blocks/actions/action_dispatch.py
funhandler/blocks/environments/__init__.py
funhandler/blocks/environments/envsys.py
funhandler/blocks/environments/trading.py
funhandler/blocks/environments/world.py
funhandler/blocks/general/__init__.py
funhandler/blocks/general/mraystorage.py
funhandler/blocks/general/performance.py
funhandler/blocks/general/portfolio.py
funhandler/stochastic/__init__.py
funhandler/stochastic/base.py
funhandler/stochastic/generators.py
funhandler/stochastic/helper.py
funhandler-0.7.3.dist-info/METADATA
funhandler-0.7.3.dist-info/WHEEL
funhandler-0.7.3.dist-info/top_level.txt
funhandler-0.7.3.dist-info/RECORD
