Metadata-Version: 2.1
Name: funhandler
Version: 0.7.3
Summary: Data handling library for forward testing
Home-page: UNKNOWN
Author: Kevin Hill
Author-email: kevin@funguana.com
License: UNKNOWN
Platform: UNKNOWN
Classifier: Programming Language :: Python :: 3
Classifier: License :: OSI Approved :: MIT License
Classifier: Operating System :: OS Independent
Requires-Dist: funpicker
Requires-Dist: funtime
Requires-Dist: apscheduler
Requires-Dist: funhouse
Requires-Dist: click
Requires-Dist: tornado
Requires-Dist: streamz-latest
Requires-Dist: dask
Requires-Dist: dask[complete]
Requires-Dist: dask[dataframe]
Requires-Dist: pyarrow
Requires-Dist: fastparquet
Requires-Dist: crayons
Requires-Dist: cerberus
Requires-Dist: python-decouple
Requires-Dist: psycopg2
